printbreakpoint/__init__.py
printbreakpoint-0.9.8.dist-info/LICENSE
printbreakpoint-0.9.8.dist-info/METADATA
printbreakpoint-0.9.8.dist-info/WHEEL
printbreakpoint-0.9.8.dist-info/top_level.txt
printbreakpoint-0.9.8.dist-info/RECORD
