Metadata-Version: 2.1
Name: printbreakpoint
Version: 0.9.8
Summary: Use breakpoint() to print out filename, line number, and data.
Home-page: https://github.com/duane9/printbreakpoint
Author: Duane Hilton
Author-email: duane9@gmail.com
Maintainer: Duane Hilton
License: MIT
Keywords: print breakpoint debugging pdb
Platform: UNKNOWN
Classifier: Programming Language :: Python :: 3.7
Classifier: Programming Language :: Python :: 3.8
Classifier: Programming Language :: Python :: 3.9
Classifier: Programming Language :: Python :: 3.10
Requires-Python: >=3.7
